{"stat.useItem.minecraft.bow":6,"stat.killEntity.EntityHorse":2,"stat.leaveGame":91,"stat.killEntity.Blaze":6,"stat.mineBlock.minecraft.sandstone":2,"stat.useItem.minecraft.mutton":15,"stat.killEntity.PigZombie":6,"stat.useItem.minecraft.planks":156,"stat.useItem.minecraft.water_bucket":107,"achievement.diamondsToYou":1,"achievement.diamonds":56,"stat.useItem.minecraft.anvil":2,"achievement.buildPickaxe":6,"stat.mineBlock.minecraft.sand":46,"stat.killEntity.Witch":1,"achievement.buildBetterPickaxe":4,"stat.hopperInspected":10,"stat.useItem.minecraft.iron_pickaxe":755,"stat.craftItem.minecraft.wooden_pickaxe":2,"stat.breakItem.minecraft.flint_and_steel":1,"stat.craftItem.minecraft.bed":1,"stat.mineBlock.minecraft.hopper":5,"stat.furnaceInteraction":79,"stat.useItem.minecraft.cooked_mutton":16,"achievement.mineWood":50,"stat.useItem.minecraft.fence":1,"stat.useItem.minecraft.stone_stairs":21,"achievement.openInventory":537,"stat.useItem.minecraft.flint_and_steel":87,"stat.mineBlock.minecraft.fence":1,"stat.useItem.minecraft.hopper":7,"stat.useItem.minecraft.dye":2,"stat.useItem.minecraft.beef":16,"stat.deaths":7,"stat.playOneMinute":690602,"stat.craftItem.minecraft.wooden_shovel":1,"stat.craftItem.minecraft.iron_pickaxe":2,"stat.mineBlock.minecraft.light_weighted_pressure_plate":1,"stat.mineBlock.minecraft.tallgrass":74,"stat.craftItem.minecraft.cooked_mutton":2,"stat.chestOpened":106,"stat.craftItem.minecraft.sign":12,"stat.useItem.minecraft.stone":7,"stat.mineBlock.minecraft.netherrack":16,"stat.fallOneCm":653490,"stat.crouchOneCm":26352,"achievement.killCow":12,"stat.mineBlock.minecraft.chest":8,"stat.craftItem.minecraft.iron_ingot":64,"stat.craftItem.minecraft.chest":10,"stat.craftItem.minecraft.hopper":2,"stat.craftingTableInteraction":67,"stat.useItem.minecraft.furnace":6,"stat.mineBlock.minecraft.gravel":18,"stat.useItem.minecraft.stone_pickaxe":29,"stat.mineBlock.minecraft.glass":9,"stat.killEntity.Rabbit":2,"stat.useItem.minecraft.wool":1,"stat.mineBlock.minecraft.dirt":173,"stat.mineBlock.minecraft.monster_egg":1,"stat.useItem.minecraft.torch":26,"stat.craftItem.minecraft.stone_stairs":16,"stat.useItem.minecraft.log":24,"stat.useItem.minecraft.cobblestone":706,"stat.craftItem.minecraft.crafting_table":5,"stat.useItem.minecraft.gravel":1,"stat.craftItem.minecraft.gold_ingot":9,"achievement.portal":16,"stat.craftItem.minecraft.bucket":1,"stat.craftItem.minecraft.planks":336,"stat.useItem.minecraft.iron_sword":91,"stat.mineBlock.minecraft.log":56,"stat.craftItem.minecraft.wooden_door":3,"stat.craftItem.minecraft.cooked_chicken":4,"stat.useItem.minecraft.wooden_door":3,"achievement.acquireIron":18,"stat.craftItem.minecraft.sugar":7,"stat.craftItem.minecraft.paper":3,"stat.craftItem.minecraft.diamond_chestplate":1,"stat.craftItem.minecraft.diamond_leggings":1,"stat.useItem.minecraft.iron_axe":19,"stat.mineBlock.minecraft.cobblestone":327,"stat.mineBlock.minecraft.yellow_flower":1,"stat.useItem.minecraft.skull":1,"stat.useItem.minecraft.diamond_sword":221,"stat.craftItem.minecraft.diamond_helmet":1,"stat.swimOneCm":110342,"achievement.buildWorkBench":6,"stat.enderchestOpened":14,"stat.breakItem.minecraft.iron_pickaxe":2,"stat.useItem.minecraft.obsidian":12,"stat.useItem.minecraft.dirt":123,"achievement.exploreAllBiomes":{"value":0,"progress":["ForestHills","Beach","Extreme Hills+","Roofed Forest","Forest","River","Plains","Taiga","Desert","Extreme Hills","Hell"]},"stat.craftItem.minecraft.furnace":5,"stat.useItem.minecraft.egg":6,"stat.craftItem.minecraft.stone_pickaxe":1,"stat.mineBlock.minecraft.obsidian":18,"stat.mineBlock.minecraft.clay":3,"stat.useItem.minecraft.stone_shovel":80,"stat.flyOneCm":612045,"stat.useItem.minecraft.cooked_beef":8,"stat.mineBlock.minecraft.iron_ore":77,"stat.craftItem.minecraft.book":1,"stat.timeSinceDeath":562717,"stat.useItem.minecraft.sign":17,"stat.craftItem.minecraft.iron_block":3,"stat.useItem.minecraft.potato":1,"stat.mineBlock.minecraft.coal_ore":69,"stat.killEntity.Creeper":20,"achievement.buildSword":1,"stat.killEntity.Squid":1,"stat.sprintOneCm":771084,"stat.mineBlock.minecraft.stone_slab":6,"stat.craftItem.minecraft.stick":32,"stat.craftItem.minecraft.wooden_axe":1,"stat.useItem.minecraft.stone_slab":11,"stat.useItem.minecraft.bed":2,"stat.mineBlock.minecraft.diamond_ore":62,"stat.mineBlock.minecraft.crafting_table":4,"stat.useItem.minecraft.diamond_pickaxe":787,"stat.useItem.minecraft.wooden_shovel":46,"stat.useItem.minecraft.bucket":116,"achievement.killEnemy":79,"achievement.buildFurnace":5,"stat.mineBlock.minecraft.planks":36,"stat.drop":29,"stat.killEntity.Sheep":27,"stat.craftItem.minecraft.diamond_pickaxe":1,"stat.killEntity.Zombie":34,"stat.craftItem.minecraft.dye":33,"stat.craftItem.minecraft.diamond_axe":1,"stat.mineBlock.minecraft.gold_ore":12,"stat.diveOneCm":41918,"stat.useItem.minecraft.diamond_axe":272,"stat.useItem.minecraft.chicken":1,"stat.mineBlock.minecraft.anvil":1,"stat.useItem.minecraft.porkchop":13,"stat.useItem.minecraft.rotten_flesh":13,"stat.craftItem.minecraft.diamond_sword":1,"stat.jump":5186,"stat.useItem.minecraft.sand":13,"stat.craftItem.minecraft.torch":20,"stat.useItem.minecraft.light_weighted_pressure_plate":1,"stat.useItem.minecraft.cooked_chicken":8,"stat.useItem.minecraft.glass":22,"stat.useItem.minecraft.sapling":3,"stat.craftItem.minecraft.flint_and_steel":2,"stat.mineBlock.minecraft.stone_stairs":5,"stat.damageTaken":6061,"stat.mineBlock.minecraft.furnace":2,"stat.mineBlock.minecraft.torch":8,"stat.useItem.minecraft.wooden_pickaxe":33,"stat.noteblockTuned":14,"stat.damageDealt":34380,"stat.craftItem.minecraft.glass":27,"stat.craftItem.minecraft.anvil":1,"stat.killEntity.Cow":13,"stat.useItem.minecraft.crafting_table":8,"stat.killEntity.Pig":7,"stat.craftItem.minecraft.stone_slab":6,"stat.walkOneCm":3019910,"stat.useItem.minecraft.chest":13,"stat.playerKills":1,"stat.useItem.minecraft.lava_bucket":8,"stat.craftItem.minecraft.diamond_boots":1,"stat.craftItem.minecraft.writable_book":1,"stat.mineBlock.minecraft.wool":1,"stat.useItem.minecraft.netherrack":15,"stat.killEntity.Skeleton":22,"stat.mineBlock.minecraft.stonebrick":4,"stat.killEntity.Chicken":17,"stat.killEntity.Spider":14,"stat.mobKills":182,"stat.mineBlock.minecraft.bookshelf":7,"stat.mineBlock.minecraft.leaves":31,"stat.useItem.minecraft.writable_book":2,"stat.mineBlock.minecraft.redstone_ore":7,"stat.mineBlock.minecraft.stone":940}