{"SURVIVAL":{"armorContents":{"0":{"==":"org.bukkit.inventory.ItemStack","type":"DIAMOND_BOOTS","damage":146,"meta":{"==":"ItemMeta","meta-type":"UNSPECIFIC","lore":["§7Springs III"],"enchants":{"Custom Enchantment":0}}},"1":{"==":"org.bukkit.inventory.ItemStack","type":"DIAMOND_LEGGINGS","damage":234,"meta":{"==":"ItemMeta","meta-type":"UNSPECIFIC","lore":["§7Cloaking IV"],"enchants":{"Custom Enchantment":0}}},"2":{"==":"org.bukkit.inventory.ItemStack","type":"DIAMOND_CHESTPLATE","damage":237,"meta":{"==":"ItemMeta","meta-type":"UNSPECIFIC","lore":["§7Obsidian Shield III"],"enchants":{"Custom Enchantment":0}}},"3":{"==":"org.bukkit.inventory.ItemStack","type":"DIAMOND_HELMET","damage":234,"meta":{"==":"ItemMeta","meta-type":"UNSPECIFIC","lore":["§7Molten III"],"enchants":{"Custom Enchantment":0}}}},"inventoryContents":{"22":{"==":"org.bukkit.inventory.ItemStack","type":"NETHERRACK"},"23":{"==":"org.bukkit.inventory.ItemStack","type":"LEATHER"},"24":{"==":"org.bukkit.inventory.ItemStack","type":"EGG","amount":3},"25":{"==":"org.bukkit.inventory.ItemStack","type":"COBBLESTONE","amount":25},"26":{"==":"org.bukkit.inventory.ItemStack","type":"WOOL","amount":12},"27":{"==":"org.bukkit.inventory.ItemStack","type":"ARROW","amount":5},"28":{"==":"org.bukkit.inventory.ItemStack","type":"COBBLESTONE_STAIRS","amount":3},"29":{"==":"org.bukkit.inventory.ItemStack","type":"RABBIT_HIDE"},"30":{"==":"org.bukkit.inventory.ItemStack","type":"SUGAR","amount":2},"31":{"==":"org.bukkit.inventory.ItemStack","type":"DIRT","amount":22},"10":{"==":"org.bukkit.inventory.ItemStack","type":"DIAMOND_BOOTS","damage":88,"meta":{"==":"ItemMeta","meta-type":"UNSPECIFIC","lore":["§7Enlighted V"],"enchants":{"Custom Enchantment":0}}},"32":{"==":"org.bukkit.inventory.ItemStack","type":"SNOW_BALL","meta":{"==":"ItemMeta","meta-type":"UNSPECIFIC","display-name":"§4Firecracker","lore":["§7§oMakes every situation a good situation!",""]}},"11":{"==":"org.bukkit.inventory.ItemStack","type":"FLINT"},"33":{"==":"org.bukkit.inventory.ItemStack","type":"GOLD_PLATE","meta":{"==":"ItemMeta","meta-type":"UNSPECIFIC","display-name":"§7Landmine","lore":["§7§oJust don't trigger it yourself, please.",""]}},"12":{"==":"org.bukkit.inventory.ItemStack","type":"QUARTZ","meta":{"==":"ItemMeta","meta-type":"UNSPECIFIC","display-name":"§bPowergloves","lore":["§7§oThrow all your problems away!",""]}},"34":{"==":"org.bukkit.inventory.ItemStack","type":"SUGAR_CANE","amount":64},"13":{"==":"org.bukkit.inventory.ItemStack","type":"GLASS","amount":5},"35":{"==":"org.bukkit.inventory.ItemStack","type":"INK_SACK","damage":15,"amount":27},"14":{"==":"org.bukkit.inventory.ItemStack","type":"RAW_BEEF","amount":3},"15":{"==":"org.bukkit.inventory.ItemStack","type":"SAND","amount":24},"16":{"==":"org.bukkit.inventory.ItemStack","type":"BONE","amount":7},"17":{"==":"org.bukkit.inventory.ItemStack","type":"SIGN"},"18":{"==":"org.bukkit.inventory.ItemStack","type":"SULPHUR","amount":3},"19":{"==":"org.bukkit.inventory.ItemStack","type":"SEEDS"},"0":{"==":"org.bukkit.inventory.ItemStack","type":"DIAMOND_AXE","damage":265},"1":{"==":"org.bukkit.inventory.ItemStack","type":"DIAMOND_SWORD","damage":178,"meta":{"==":"ItemMeta","meta-type":"UNSPECIFIC","display-name":"THE THUNDER","lore":["§7Thunderingblow III"],"repair-cost":1}},"2":{"==":"org.bukkit.inventory.ItemStack","type":"DIAMOND_PICKAXE","damage":772},"3":{"==":"org.bukkit.inventory.ItemStack","type":"WATER_BUCKET"},"4":{"==":"org.bukkit.inventory.ItemStack","type":"FLINT_AND_STEEL","damage":2,"meta":{"==":"ItemMeta","meta-type":"UNSPECIFIC","display-name":"4Flamethrower","lore":["§7§oBurn, baby, burn!",""],"repair-cost":1}},"5":{"==":"org.bukkit.inventory.ItemStack","type":"OBSIDIAN","amount":4},"6":{"==":"org.bukkit.inventory.ItemStack","type":"LEASH","amount":50},"7":{"==":"org.bukkit.inventory.ItemStack","type":"CLAY_BALL","amount":12},"8":{"==":"org.bukkit.inventory.ItemStack","type":"RECORD_8"},"9":{"==":"org.bukkit.inventory.ItemStack","type":"IRON_INGOT","amount":4},"20":{"==":"org.bukkit.inventory.ItemStack","type":"SANDSTONE","amount":2},"21":{"==":"org.bukkit.inventory.ItemStack","type":"SAPLING"}},"bedSpawnLocation":{"wo":"survivalpr","x":-93.0,"ya":0.0,"y":64.0,"pi":0.0,"z":-153.0},"potions":"[{\"pa\":4,\"pt\":8,\"pd\":598617},{\"pa\":2,\"pt\":12,\"pd\":598717},{\"pa\":0,\"pt\":14,\"pd\":191}]","enderChestContents":{"0":{"==":"org.bukkit.inventory.ItemStack","type":"DIAMOND","amount":12},"1":{"==":"org.bukkit.inventory.ItemStack","type":"GOLD_INGOT","amount":4}},"stats":{"ex":"3.2400715","ma":"300","fl":"15","el":"22","hp":"19.399999618530273","xp":"0.5831645","txp":"1333","ft":"-20","fd":"0.0","sa":"0.0","ra":"300"}}}